Metadata-Version: 2.1
Name: pypropat
Version: 0.0.1
Summary: Python package for a test
Home-page: https://github.com/MichaelBentlyOh/pypropat
Author: Oh Min Sik,Kim Gwan Young,Joo Sang Hyun 
Author-email: michael1015999@gmail.com
Keywords: orbit,space,spacecraft
Requires-Python: >=3.7
License-File: LICENSE.txt
